[
  {
    "line": 1,
    "elements": [
      {
        "start_timestamp": "2019-05-04T20:41:14.929Z",
        "line": 5,
        "name": "Title of your scenario",
        "description": "",
        "id": "title-of-your-feature;title-of-your-scenario",
        "after": [
          {
            "result": {
              "duration": 172658159,
              "status": "passed"
            },
            "match": {
              "location": "Hooks.setUp()"
            }
          }
        ],
        "type": "scenario",
        "keyword": "Scenario",
        "steps": [
          {
            "result": {
              "duration": 6741580664,
              "status": "passed"
            },
            "line": 6,
            "name": "I am on home page",
            "match": {
              "location": "GoogleSearch.i_am_on_home_page()"
            },
            "keyword": "Given "
          },
          {
            "result": {
              "duration": 1481877005,
              "status": "passed"
            },
            "line": 7,
            "name": "search for something",
            "match": {
              "location": "GoogleSearch.search_for_something()"
            },
            "keyword": "Then "
          }
        ]
      }
    ],
    "name": "Title of your feature",
    "description": "  I want to use this template for my feature file",
    "id": "title-of-your-feature",
    "keyword": "Feature",
    "uri": "file:src/test/resources/functionaltests/test.feature",
    "tags": []
  }
]